pyfactory
