Metadata-Version: 1.0
Name: pyfactory
Version: 0.3.0
Summary: Generic model factory framework
Home-page: https://kiip.github.com/pyfactory/
Author: Mitchell Hashimoto
Author-email: mitchell@kiip.me
License: MIT License
Keywords: factory,pyfactory,model
Platform: UNKNOWN
Classifier: Development Status :: 4 - Beta
Classifier: Intended Audience :: Developers
Classifier: License :: OSI Approved :: MIT License
Classifier: Operating System :: OS Independent
Classifier: Programming Language :: Python
Classifier: Topic :: Software Development :: Testing
